okra_py/__init__.py
okra_py/auth.py
okra_py/balance.py
okra_py/base.py
okra_py/errors.py
okra_py/identity.py
okra_py/income.py
okra_py/transaction.py
okra_py_official-1.1.dist-info/METADATA
okra_py_official-1.1.dist-info/WHEEL
okra_py_official-1.1.dist-info/top_level.txt
okra_py_official-1.1.dist-info/RECORD
