Metadata-Version: 2.1
Name: okra-py-official
Version: 1.1
Summary: Python wrapper for Okra API
Home-page: https://github.com/okraHQ/okra_py
Author: Okra
Author-email: tech@okra.ng
License: Apache License 2.0
Platform: UNKNOWN
Requires-Dist: requests
